pybegin/__init__.py
pybegin/hello.py
pybegin-0.0.1.dist-info/METADATA
pybegin-0.0.1.dist-info/WHEEL
pybegin-0.0.1.dist-info/top_level.txt
pybegin-0.0.1.dist-info/RECORD
