Metadata-Version: 2.1
Name: pybegin
Version: 0.0.1
Summary: Lets get started
Home-page: http://intel.com/someplace
Author: Tsemach Mizrachi
Author-email: tsemach.mizachi@intelc.om
License: UNKNOWN
Keywords: pip,geospatail,begin
Platform: UNKNOWN
